.coveragerc
.readthedocs.yml
.travis.yml
AUTHORS
ChangeLog
Readme.rst
requirements.txt
setup.cfg
setup.py
test-requirements.txt
tox.ini
.github/CONTRIBUTING.md
docs/Makefile
docs/make.bat
docs/source/conf.py
docs/source/index.rst
shortmagnet/__init__.py
shortmagnet.egg-info/PKG-INFO
shortmagnet.egg-info/SOURCES.txt
shortmagnet.egg-info/dependency_links.txt
shortmagnet.egg-info/entry_points.txt
shortmagnet.egg-info/not-zip-safe
shortmagnet.egg-info/pbr.json
shortmagnet.egg-info/requires.txt
shortmagnet.egg-info/top_level.txt
tests/__init__.py
tests/features/package.feature
tests/features/shortener.feature
tests/features/steps/steps_main.py
tests/features/steps/steps_package.py
tests/fixtures/main.conf
tests/unit/__init__.py
tests/unit/test_main.py
tests/unit/test_package.py