Metadata-Version: 1.0
Name: shortmagnet
Version: 0.0.1.dev11
Summary: Magnet-oriented URL Shortener.
Home-page: http://github.com/xayon/shortmagnet
Author: David Francos
Author-email: opensource@davidfrancos.net
License: GPL3+
Platform: UNKNOWN
